web3_calculator/__init__.py
web3_calculator-0.1.1.dist-info/LICENSE
web3_calculator-0.1.1.dist-info/METADATA
web3_calculator-0.1.1.dist-info/WHEEL
web3_calculator-0.1.1.dist-info/top_level.txt
web3_calculator-0.1.1.dist-info/RECORD
