Metadata-Version: 2.1
Name: web3-calculator
Version: 0.1.1
Summary: A simple web3 calculator package
Home-page: https://github.com/Zcb991/web3-calculator
Author: Zcb991
Author-email: 2952964392@qq.com
Project-URL: Source, https://github.com/Zcb991/web3-calculator
Classifier: Programming Language :: Python :: 3
Classifier: License :: OSI Approved :: MIT License
Classifier: Operating System :: OS Independent
License-File: LICENSE
Requires-Dist: requests
Requires-Dist: pandas
